proximus/__init__.py
proximus-0.0.2.dist-info/LICENSE
proximus-0.0.2.dist-info/METADATA
proximus-0.0.2.dist-info/WHEEL
proximus-0.0.2.dist-info/top_level.txt
proximus-0.0.2.dist-info/RECORD
