Metadata-Version: 2.1
Name: proximus
Version: 0.0.2
Summary: A web automation of Bbox3 web interface.
Home-page: https://codeberg.org/SnowCode/bbox3
Author: SnowCode
License: UNKNOWN
Platform: UNKNOWN
